drjit/libdrjit-extra.dylib
drjit/_sh_eval.py
drjit/interop.pyi
drjit/config.py
drjit/__init__.pyi
drjit/nn.py
drjit/stubs.pat
drjit/ast.pyi
drjit/__init__.py
drjit/detail.pyi
drjit/opt.py
drjit/random.py
drjit/libdrjit-core.dylib
drjit/interop.py
drjit/_drjit_ext.abi3.so
drjit/hashgrid.py
drjit/detail.py
drjit/dda.py
drjit/ast.py
drjit/py.typed
drjit/_reduce.py
drjit/libnanothread.dylib
drjit/cmake/drjit/drjitTargets.cmake
drjit/cmake/drjit/drjitConfig.cmake
drjit/cmake/drjit/drjitTargets-release.cmake
drjit/cmake/drjit/drjitConfigVersion.cmake
drjit/auto/__init__.pyi
drjit/auto/__init__.py
drjit/auto/ad.pyi
drjit/auto/py.typed
drjit/auto/ad.py
drjit/include/drjit/morton.h
drjit/include/drjit/fwd.h
drjit/include/drjit/resample.h
drjit/include/drjit/packet_intrin.h
drjit/include/drjit/custom.h
drjit/include/drjit/sh_eval.h
drjit/include/drjit/map.h
drjit/include/drjit/array_static.h
drjit/include/drjit/array_iface.h
drjit/include/drjit/sphere.h
drjit/include/drjit/array_traverse.h
drjit/include/drjit/packet_sse42.h
drjit/include/drjit/quaternion.h
drjit/include/drjit/matrix.h
drjit/include/drjit/color.h
drjit/include/drjit/array_base.h
drjit/include/drjit/dynamic.h
drjit/include/drjit/call.h
drjit/include/drjit/array_router.h
drjit/include/drjit/array_format.h
drjit/include/drjit/idiv.h
drjit/include/drjit/packet_avx2.h
drjit/include/drjit/packet_kmask.h
drjit/include/drjit/array_traits.h
drjit/include/drjit/jit.h
drjit/include/drjit/packet_neon.h
drjit/include/drjit/array_mask.h
drjit/include/drjit/traversable_base.h
drjit/include/drjit/packet.h
drjit/include/drjit/extra.h
drjit/include/drjit/array.h
drjit/include/drjit/transform.h
drjit/include/drjit/util.h
drjit/include/drjit/array_utils.h
drjit/include/drjit/math.h
drjit/include/drjit/packet_avx512.h
drjit/include/drjit/texture.h
drjit/include/drjit/array_generic.h
drjit/include/drjit/autodiff.h
drjit/include/drjit/packet_recursive.h
drjit-1.2.0.dist-info/RECORD
drjit-1.2.0.dist-info/WHEEL
drjit-1.2.0.dist-info/METADATA
drjit-1.2.0.dist-info/licenses/LICENSE
