Metadata-Version: 2.1
Name: drjit
Version: 1.2.0
Summary: Dr.Jit: A Just-In-Time Compiler for Differentiable Rendering
Author-Email: Wenzel Jakob <wenzel.jakob@epfl.ch>, =?utf-8?q?Christian_D=C3=B6ring?= <christian.doering@tum.de>, Nicolas Roussel <nicolas.roussel@epfl.ch>, =?utf-8?q?S=C3=A9bastien_Speierer?= <sebastien.speierer@epfl.ch>, Delio Vicini <delio.vicini@epfl.ch>
Classifier: License :: OSI Approved :: BSD License
Project-URL: Homepage, https://github.com/mitsuba-renderer/drjit
Requires-Python: >=3.8
Requires-Dist: typing_extensions; python_version < "3.11"
